unknown_pixels-1.1.0.dist-info/licenses/LICENSE
unknownpixels/__init__.py
unknownpixels/_version.py
unknownpixels/image.py
unknownpixels/unknownpixels.py
unknownpixels/video.py
unknown_pixels-1.1.0.dist-info/METADATA
unknown_pixels-1.1.0.dist-info/WHEEL
unknown_pixels-1.1.0.dist-info/entry_points.txt
unknown_pixels-1.1.0.dist-info/top_level.txt
unknown_pixels-1.1.0.dist-info/RECORD
