Metadata-Version: 2.4
Name: unknown-pixels
Version: 1.1.0
Summary: Convert images into Unknown Pleasures-style waveform art.
Author-email: Will Roper <w.roper@sussex.ac.uk>, Stephen Wilkins <s.wilkins@sussex.ac.uk>
Requires-Python: >=3.8
License-File: LICENSE
Requires-Dist: numpy
Requires-Dist: matplotlib
Requires-Dist: Pillow
Requires-Dist: scipy
Requires-Dist: moviepy
Provides-Extra: dev
Requires-Dist: ruff==0.11.7; extra == "dev"
Requires-Dist: pre-commit; extra == "dev"
Provides-Extra: test
Requires-Dist: pytest; extra == "test"
Dynamic: license-file
